{
  "adr_ids": [
    "ADR-AGEIX-ARCH-GUIDANCE",
    "ADR-AGEIX-ARCH-REGISTRY",
    "ADR-AGEIX-CONSULTATION",
    "ADR-AGEIX-EVIDENCE-FRESHNESS",
    "ADR-AGEIX-EVIDENCE-PACKAGES",
    "ADR-AGEIX-GOVERNANCE-FIRST",
    "ADR-AGEIX-GUIDECTX",
    "ADR-AGEIX-MCP-DISCOVERY",
    "ADR-AGEIX-MCP-REGISTRY",
    "ADR-AGEIX-OAUTH-JWT",
    "ADR-AGEIX-SELF-ARCH",
    "ADR-AGEIX-TRUST-BOUNDARY",
    "ADR-AGEIX-WORKCTX"
  ],
  "approved_at": "2026-06-24T19:26:40.636717+00:00",
  "approved_by": "chair",
  "architecture_ids": [
    "ARCH-AGEIX-PROJECT",
    "ARCH-AGEIX-EVIDENCEPLATFORM",
    "ARCH-AGEIX-ARCHITECTUREPLATFORM"
  ],
  "created_at": "2026-06-24T19:26:40.636727+00:00",
  "created_by": "architecture_baseline_service",
  "decision_trace_id": "TRACE-BASELINE-PRIN-0002",
  "evidence_package_ids": [],
  "metadata": {
    "canonical_ageix_baseline": true,
    "seeded_by": "sprint_18_10"
  },
  "principle_id": "ARCHPRIN-AGEIX-EVIDENCE-FIRST",
  "principle_number": "PRIN-0002",
  "project_id": "Ageix",
  "proposal_id": "PROP-BASELINE-PRIN-0002",
  "rationale": "Evidence gives decisions a stable factual basis and preserves explainability.",
  "related_principle_ids": [],
  "revision_ids": [],
  "scope": "project",
  "statement": "Architectural and implementation decisions should be supported by scoped evidence packages where available.",
  "status": "accepted",
  "supersedes_principle_id": null,
  "title": "Evidence before decisions"
}