{
  "version": 1,
  "repair": {
    "max_local_attempts": 3,
    "allow_cloud_escalation": true,
    "max_cloud_attempts": 1
  },
  "cloud": {
    "max_context_tokens": 6000,
    "max_evidence_items": 8,
    "max_failure_summary_chars": 4000,
    "allow_full_logs": false,
    "allow_full_file_contents": false
  },
  "validation": {
    "require_validation": true,
    "allow_validation_bypass": false
  },
  "governance": {
    "require_human_review": true,
    "allow_auto_promotion": false,
    "allow_auto_commit": false,
    "allow_direct_repo_modification": false
  },
  "promotion_confidence": {
    "enabled": true,
    "minimum_confidence": 0.8,
    "ratings": {
      "high": 0.9,
      "medium": 0.75,
      "low": 0.5
    },
    "weights": {
      "proposal_quality": 0.2,
      "requirement_traceability": 0.2,
      "behavioral_verification": 0.2,
      "validation_evidence": 0.2,
      "runtime_execution": 0.2
    }
  },
  "promotion_governance": {
    "enabled": true,
    "human_approval_required": true,
    "minimum_confidence": 0.8,
    "allow_promotion_with_blockers": false
  },
  "dependency_intelligence": {
    "enabled": true,
    "max_depth": 2,
    "max_nodes": 50,
    "max_imports_per_file": 25,
    "follow_test_imports": true,
    "follow_runtime_imports": true,
    "allow_proposed_local_imports": true,
    "allow_existing_local_imports": true,
    "allow_stdlib_imports": true,
    "allowed_test_dependencies": [
      "pytest"
    ],
    "blocked_dependencies": [],
    "unknown_dependency_policy": "fail"
  },
  "repository_impact": {
    "enabled": true,
    "max_depth": 2,
    "max_nodes": 75,
    "max_dependents_per_file": 25,
    "retry_on_limit": true,
    "retry_max_depth": 4,
    "retry_max_nodes": 200,
    "retry_max_dependents_per_file": 75,
    "retry_policy": "validation_failure_only",
    "include_tests": true,
    "include_runtime_files": true,
    "include_companion_tests": true,
    "impacted_test_depth": 1,
    "auto_add_companion_tests": true,
    "auto_add_impacted_tests": true,
    "recommend_indirect_dependents": true,
    "circular_dependency_policy": "warn_stop_path",
    "unresolved_import_policy": "warn",
    "unknown_impact_policy": "warn",
    "limit_policy": "warn",
    "exclude_paths": [
      ".git/",
      ".pytest_cache/",
      ".mypy_cache/",
      ".ruff_cache/",
      "__pycache__/",
      "venv/",
      ".venv/",
      "env/",
      ".env/",
      "site-packages/",
      "node_modules/",
      "build/",
      "dist/",
      "*.egg-info/",
      "artifacts/",
      "htmlcov/",
      ".tox/",
      ".ageix/staged/",
      ".ageix/staging/",
      ".ageix/manifests/",
      ".ageix/runs/",
      ".ageix/runtime/",
      ".ageix/verification/",
      ".ageix/repair_loops/",
      ".ageix/logs/"
    ]
  },
  "cloud_context": {
    "include_impact_summary": true,
    "include_full_impact_evidence": false,
    "max_impact_items": 10
  }
}